{"defaultSlide":{"components":[{"topY":0,"color":"0 0 0","topX":0,"rotation":0,"bottomX":3,"width":5,"bottomY":98,"type":"Line","content":"3 98 3 98"},{"topY":0,"color":"0 0 0","topX":0,"rotation":0,"bottomX":4,"width":5,"bottomY":96,"type":"Line","content":"4 96 4 96"},{"topY":0,"color":"0 0 0","topX":0,"rotation":0,"bottomX":5,"width":5,"bottomY":95,"type":"Line","content":"5 95 5 95"},{"topY":0,"color":"0 0 0","topX":0,"rotation":0,"bottomX":7,"width":5,"bottomY":94,"type":"Line","content":"7 94 7 94"},{"topY":0,"color":"0 0 0","topX":0,"rotation":0,"bottomX":7,"width":5,"bottomY":93,"type":"Line","content":"7 93 7 93"},{"topY":0,"color":"0 0 0","topX":0,"rotation":0,"bottomX":8,"width":5,"bottomY":92,"type":"Line","content":"8 92 8 92"},{"topY":0,"color":"0 0 0","topX":0,"rotation":0,"bottomX":9,"width":5,"bottomY":91,"type":"Line","content":"9 91 9 91"},{"topY":0,"color":"0 0 0","topX":0,"rotation":0,"bottomX":10,"width":5,"bottomY":90,"type":"Line","content":"10 90 10 90"},{"topY":0,"color":"0 0 0","topX":0,"rotation":0,"bottomX":11,"width":5,"bottomY":89,"type":"Line","content":"11 89 11 89"},{"topY":0,"color":"0 0 0","topX":0,"rotation":0,"bottomX":14,"width":5,"bottomY":87,"type":"Line","content":"14 87 14 87"},{"topY":0,"color":"0 0 0","topX":0,"rotation":0,"bottomX":16,"width":5,"bottomY":85,"type":"Line","content":"16 85 16 85"},{"topY":0,"color":"0 0 0","topX":0,"rotation":0,"bottomX":19,"width":5,"bottomY":83,"type":"Line","content":"19 83 19 83"},{"topY":0,"color":"0 0 0","topX":0,"rotation":0,"bottomX":23,"width":5,"bottomY":81,"type":"Line","content":"23 81 23 81"},{"topY":0,"color":"0 0 0","topX":0,"rotation":0,"bottomX":24,"width":5,"bottomY":80,"type":"Line","content":"24 80 24 80"},{"topY":0,"color":"0 0 0","topX":0,"rotation":0,"bottomX":25,"width":5,"bottomY":79,"type":"Line","content":"25 79 25 79"},{"topY":0,"color":"0 0 0","topX":0,"rotation":0,"bottomX":27,"width":5,"bottomY":78,"type":"Line","content":"27 78 27 78"},{"topY":0,"color":"0 0 0","topX":0,"rotation":0,"bottomX":28,"width":5,"bottomY":77,"type":"Line","content":"28 77 28 77"},{"topY":0,"color":"0 0 0","topX":0,"rotation":0,"bottomX":29,"width":5,"bottomY":76,"type":"Line","content":"29 76 29 76"},{"topY":0,"color":"0 0 0","topX":0,"rotation":0,"bottomX":29,"width":5,"bottomY":75,"type":"Line","content":"29 75 29 75"},{"topY":0,"color":"0 0 0","topX":0,"rotation":0,"bottomX":30,"width":5,"bottomY":75,"type":"Line","content":"30 75 30 75"},{"topY":0,"color":"0 0 0","topX":0,"rotation":0,"bottomX":31,"width":5,"bottomY":74,"type":"Line","content":"31 74 31 74"},{"topY":0,"color":"0 0 0","topX":0,"rotation":0,"bottomX":31,"width":5,"bottomY":73,"type":"Line","content":"31 73 31 73"},{"topY":0,"color":"0 0 0","topX":0,"rotation":0,"bottomX":31,"width":5,"bottomY":73,"type":"Line","content":"31 73 31 73"},{"topY":0,"color":"0 0 0","topX":0,"rotation":0,"bottomX":31,"width":5,"bottomY":73,"type":"Line","content":"31 73 31 73"},{"topY":0,"color":"0 0 0","topX":0,"rotation":0,"bottomX":32,"width":5,"bottomY":72,"type":"Line","content":"32 72 32 72"},{"topY":0,"color":"0 0 0","topX":0,"rotation":0,"bottomX":33,"width":5,"bottomY":72,"type":"Line","content":"33 72 33 72"},{"topY":0,"color":"0 0 0","topX":0,"rotation":0,"bottomX":33,"width":5,"bottomY":71,"type":"Line","content":"33 71 33 71"},{"topY":0,"color":"0 0 0","topX":0,"rotation":0,"bottomX":33,"width":5,"bottomY":71,"type":"Line","content":"33 71 33 71"},{"topY":0,"color":"0 0 0","topX":0,"rotation":0,"bottomX":34,"width":5,"bottomY":71,"type":"Line","content":"34 71 34 71"},{"topY":0,"color":"0 0 0","topX":0,"rotation":0,"bottomX":34,"width":5,"bottomY":70,"type":"Line","content":"34 70 34 70"},{"topY":0,"color":"0 0 0","topX":0,"rotation":0,"bottomX":35,"width":5,"bottomY":70,"type":"Line","content":"35 70 35 70"},{"topY":0,"color":"0 0 0","topX":0,"rotation":0,"bottomX":35,"width":5,"bottomY":69,"type":"Line","content":"35 69 35 69"},{"topY":0,"color":"0 0 0","topX":0,"rotation":0,"bottomX":35,"width":5,"bottomY":69,"type":"Line","content":"35 69 35 69"},{"topY":0,"color":"0 0 0","topX":0,"rotation":0,"bottomX":36,"width":5,"bottomY":69,"type":"Line","content":"36 69 36 69"},{"topY":0,"color":"0 0 0","topX":0,"rotation":0,"bottomX":36,"width":5,"bottomY":68,"type":"Line","content":"36 68 36 68"},{"topY":0,"color":"0 0 0","topX":0,"rotation":0,"bottomX":37,"width":5,"bottomY":68,"type":"Line","content":"37 68 37 68"},{"topY":0,"color":"0 0 0","topX":0,"rotation":0,"bottomX":37,"width":5,"bottomY":67,"type":"Line","content":"37 67 37 67"},{"topY":0,"color":"0 0 0","topX":0,"rotation":0,"bottomX":37,"width":5,"bottomY":67,"type":"Line","content":"37 67 37 67"},{"topY":0,"color":"0 0 0","topX":0,"rotation":0,"bottomX":39,"width":5,"bottomY":66,"type":"Line","content":"39 66 39 66"},{"topY":0,"color":"0 0 0","topX":0,"rotation":0,"bottomX":40,"width":5,"bottomY":65,"type":"Line","content":"40 65 40 65"},{"topY":0,"color":"0 0 0","topX":0,"rotation":0,"bottomX":41,"width":5,"bottomY":64,"type":"Line","content":"41 64 41 64"},{"topY":0,"color":"0 0 0","topX":0,"rotation":0,"bottomX":42,"width":5,"bottomY":64,"type":"Line","content":"42 64 42 64"},{"topY":0,"color":"0 0 0","topX":0,"rotation":0,"bottomX":43,"width":5,"bottomY":63,"type":"Line","content":"43 63 43 63"},{"topY":0,"color":"0 0 0","topX":0,"rotation":0,"bottomX":44,"width":5,"bottomY":63,"type":"Line","content":"44 63 44 63"},{"topY":0,"color":"0 0 0","topX":0,"rotation":0,"bottomX":45,"width":5,"bottomY":62,"type":"Line","content":"45 62 45 62"},{"topY":0,"color":"0 0 0","topX":0,"rotation":0,"bottomX":46,"width":5,"bottomY":61,"type":"Line","content":"46 61 46 61"},{"topY":0,"color":"0 0 0","topX":0,"rotation":0,"bottomX":47,"width":5,"bottomY":61,"type":"Line","content":"47 61 47 61"},{"topY":0,"color":"0 0 0","topX":0,"rotation":0,"bottomX":49,"width":5,"bottomY":61,"type":"Line","content":"49 61 49 61"},{"topY":0,"color":"0 0 0","topX":0,"rotation":0,"bottomX":49,"width":5,"bottomY":60,"type":"Line","content":"49 60 49 60"},{"topY":0,"color":"0 0 0","topX":0,"rotation":0,"bottomX":50,"width":5,"bottomY":60,"type":"Line","content":"50 60 50 60"},{"topY":0,"color":"0 0 0","topX":0,"rotation":0,"bottomX":51,"width":5,"bottomY":59,"type":"Line","content":"51 59 51 59"},{"topY":0,"color":"0 0 0","topX":0,"rotation":0,"bottomX":52,"width":5,"bottomY":59,"type":"Line","content":"52 59 52 59"},{"topY":0,"color":"0 0 0","topX":0,"rotation":0,"bottomX":53,"width":5,"bottomY":59,"type":"Line","content":"53 59 53 59"},{"topY":0,"color":"0 0 0","topX":0,"rotation":0,"bottomX":53,"width":5,"bottomY":59,"type":"Line","content":"53 59 53 59"},{"topY":0,"color":"0 0 0","topX":0,"rotation":0,"bottomX":54,"width":5,"bottomY":59,"type":"Line","content":"54 59 54 59"},{"topY":0,"color":"0 0 0","topX":0,"rotation":0,"bottomX":55,"width":5,"bottomY":58,"type":"Line","content":"55 58 55 58"},{"topY":0,"color":"0 0 0","topX":0,"rotation":0,"bottomX":56,"width":5,"bottomY":57,"type":"Line","content":"56 57 56 57"},{"topY":0,"color":"0 0 0","topX":0,"rotation":0,"bottomX":57,"width":5,"bottomY":57,"type":"Line","content":"57 57 57 57"},{"topY":0,"color":"0 0 0","topX":0,"rotation":0,"bottomX":59,"width":5,"bottomY":55,"type":"Line","content":"59 55 59 55"},{"topY":0,"color":"0 0 0","topX":0,"rotation":0,"bottomX":60,"width":5,"bottomY":55,"type":"Line","content":"60 55 60 55"},{"topY":0,"color":"0 0 0","topX":0,"rotation":0,"bottomX":61,"width":5,"bottomY":54,"type":"Line","content":"61 54 61 54"},{"topY":0,"color":"0 0 0","topX":0,"rotation":0,"bottomX":61,"width":5,"bottomY":53,"type":"Line","content":"61 53 61 53"},{"topY":0,"color":"0 0 0","topX":0,"rotation":0,"bottomX":61,"width":5,"bottomY":52,"type":"Line","content":"61 52 61 52"},{"topY":0,"color":"0 0 0","topX":0,"rotation":0,"bottomX":62,"width":5,"bottomY":52,"type":"Line","content":"62 52 62 52"},{"topY":0,"color":"0 0 0","topX":0,"rotation":0,"bottomX":62,"width":5,"bottomY":51,"type":"Line","content":"62 51 62 51"},{"topY":0,"color":"0 0 0","topX":0,"rotation":0,"bottomX":63,"width":5,"bottomY":51,"type":"Line","content":"63 51 63 51"},{"topY":0,"color":"0 0 0","topX":0,"rotation":0,"bottomX":63,"width":5,"bottomY":50,"type":"Line","content":"63 50 63 50"},{"topY":0,"color":"0 0 0","topX":0,"rotation":0,"bottomX":63,"width":5,"bottomY":49,"type":"Line","content":"63 49 63 49"},{"topY":0,"color":"0 0 0","topX":0,"rotation":0,"bottomX":64,"width":5,"bottomY":48,"type":"Line","content":"64 48 64 48"},{"topY":0,"color":"0 0 0","topX":0,"rotation":0,"bottomX":65,"width":5,"bottomY":47,"type":"Line","content":"65 47 65 47"},{"topY":0,"color":"0 0 0","topX":0,"rotation":0,"bottomX":65,"width":5,"bottomY":47,"type":"Line","content":"65 47 65 47"},{"topY":0,"color":"0 0 0","topX":0,"rotation":0,"bottomX":66,"width":5,"bottomY":47,"type":"Line","content":"66 47 66 47"},{"topY":0,"color":"0 0 0","topX":0,"rotation":0,"bottomX":66,"width":5,"bottomY":47,"type":"Line","content":"66 47 66 47"},{"topY":0,"color":"0 0 0","topX":0,"rotation":0,"bottomX":67,"width":5,"bottomY":46,"type":"Line","content":"67 46 67 46"},{"topY":0,"color":"0 0 0","topX":0,"rotation":0,"bottomX":67,"width":5,"bottomY":45,"type":"Line","content":"67 45 67 45"},{"topY":0,"color":"0 0 0","topX":0,"rotation":0,"bottomX":68,"width":5,"bottomY":45,"type":"Line","content":"68 45 68 45"},{"topY":0,"color":"0 0 0","topX":0,"rotation":0,"bottomX":69,"width":5,"bottomY":44,"type":"Line","content":"69 44 69 44"},{"topY":0,"color":"0 0 0","topX":0,"rotation":0,"bottomX":69,"width":5,"bottomY":43,"type":"Line","content":"69 43 69 43"},{"topY":0,"color":"0 0 0","topX":0,"rotation":0,"bottomX":70,"width":5,"bottomY":43,"type":"Line","content":"70 43 70 43"},{"topY":0,"color":"0 0 0","topX":0,"rotation":0,"bottomX":71,"width":5,"bottomY":43,"type":"Line","content":"71 43 71 43"},{"topY":0,"color":"0 0 0","topX":0,"rotation":0,"bottomX":71,"width":5,"bottomY":42,"type":"Line","content":"71 42 71 42"},{"topY":0,"color":"0 0 0","topX":0,"rotation":0,"bottomX":71,"width":5,"bottomY":41,"type":"Line","content":"71 41 71 41"},{"topY":0,"color":"0 0 0","topX":0,"rotation":0,"bottomX":71,"width":5,"bottomY":41,"type":"Line","content":"71 41 71 41"},{"topY":0,"color":"0 0 0","topX":0,"rotation":0,"bottomX":71,"width":5,"bottomY":41,"type":"Line","content":"71 41 71 41"},{"topY":0,"color":"0 0 0","topX":0,"rotation":0,"bottomX":72,"width":5,"bottomY":40,"type":"Line","content":"72 40 72 40"},{"topY":0,"color":"0 0 0","topX":0,"rotation":0,"bottomX":73,"width":5,"bottomY":40,"type":"Line","content":"73 40 73 40"},{"topY":0,"color":"0 0 0","topX":0,"rotation":0,"bottomX":73,"width":5,"bottomY":39,"type":"Line","content":"73 39 73 39"},{"topY":0,"color":"0 0 0","topX":0,"rotation":0,"bottomX":74,"width":5,"bottomY":39,"type":"Line","content":"74 39 74 39"},{"topY":0,"color":"0 0 0","topX":0,"rotation":0,"bottomX":75,"width":5,"bottomY":37,"type":"Line","content":"75 37 75 37"},{"topY":0,"color":"0 0 0","topX":0,"rotation":0,"bottomX":75,"width":5,"bottomY":36,"type":"Line","content":"75 36 75 36"},{"topY":0,"color":"0 0 0","topX":0,"rotation":0,"bottomX":77,"width":5,"bottomY":35,"type":"Line","content":"77 35 77 35"},{"topY":0,"color":"0 0 0","topX":0,"rotation":0,"bottomX":78,"width":5,"bottomY":33,"type":"Line","content":"78 33 78 33"},{"topY":0,"color":"0 0 0","topX":0,"rotation":0,"bottomX":79,"width":5,"bottomY":32,"type":"Line","content":"79 32 79 32"},{"topY":0,"color":"0 0 0","topX":0,"rotation":0,"bottomX":81,"width":5,"bottomY":31,"type":"Line","content":"81 31 81 31"},{"topY":0,"color":"0 0 0","topX":0,"rotation":0,"bottomX":82,"width":5,"bottomY":31,"type":"Line","content":"82 31 82 31"},{"topY":0,"color":"0 0 0","topX":0,"rotation":0,"bottomX":83,"width":5,"bottomY":31,"type":"Line","content":"83 31 83 31"},{"topY":0,"color":"0 0 0","topX":0,"rotation":0,"bottomX":83,"width":5,"bottomY":31,"type":"Line","content":"83 31 83 31"},{"topY":0,"color":"0 0 0","topX":0,"rotation":0,"bottomX":84,"width":5,"bottomY":31,"type":"Line","content":"84 31 84 31"},{"topY":0,"color":"0 0 0","topX":0,"rotation":0,"bottomX":85,"width":5,"bottomY":30,"type":"Line","content":"85 30 85 30"},{"topY":0,"color":"0 0 0","topX":0,"rotation":0,"bottomX":86,"width":5,"bottomY":30,"type":"Line","content":"86 30 86 30"},{"topY":0,"color":"0 0 0","topX":0,"rotation":0,"bottomX":87,"width":5,"bottomY":29,"type":"Line","content":"87 29 87 29"},{"topY":0,"color":"0 0 0","topX":0,"rotation":0,"bottomX":87,"width":5,"bottomY":29,"type":"Line","content":"87 29 87 29"},{"topY":0,"color":"0 0 0","topX":0,"rotation":0,"bottomX":88,"width":5,"bottomY":28,"type":"Line","content":"88 28 88 28"},{"topY":0,"color":"0 0 0","topX":0,"rotation":0,"bottomX":89,"width":5,"bottomY":28,"type":"Line","content":"89 28 89 28"},{"topY":0,"color":"0 0 0","topX":0,"rotation":0,"bottomX":89,"width":5,"bottomY":28,"type":"Line","content":"89 28 89 28"},{"topY":0,"color":"0 0 0","topX":0,"rotation":0,"bottomX":90,"width":5,"bottomY":28,"type":"Line","content":"90 28 90 28"},{"topY":0,"color":"0 0 0","topX":0,"rotation":0,"bottomX":90,"width":5,"bottomY":27,"type":"Line","content":"90 27 90 27"},{"topY":0,"color":"0 0 0","topX":0,"rotation":0,"bottomX":91,"width":5,"bottomY":27,"type":"Line","content":"91 27 91 27"},{"topY":0,"color":"0 0 0","topX":0,"rotation":0,"bottomX":91,"width":5,"bottomY":27,"type":"Line","content":"91 27 91 27"},{"topY":0,"color":"0 0 0","topX":0,"rotation":0,"bottomX":92,"width":5,"bottomY":26,"type":"Line","content":"92 26 92 26"},{"topY":0,"color":"0 0 0","topX":0,"rotation":0,"bottomX":93,"width":5,"bottomY":25,"type":"Line","content":"93 25 93 25"},{"topY":0,"color":"0 0 0","topX":0,"rotation":0,"bottomX":94,"width":5,"bottomY":23,"type":"Line","content":"94 23 94 23"},{"topY":0,"color":"0 0 0","topX":0,"rotation":0,"bottomX":95,"width":5,"bottomY":23,"type":"Line","content":"95 23 95 23"},{"topY":0,"color":"0 0 0","topX":0,"rotation":0,"bottomX":96,"width":5,"bottomY":22,"type":"Line","content":"96 22 96 22"},{"topY":0,"color":"0 0 0","topX":0,"rotation":0,"bottomX":97,"width":5,"bottomY":22,"type":"Line","content":"97 22 97 22"},{"topY":0,"color":"0 0 0","topX":0,"rotation":0,"bottomX":97,"width":5,"bottomY":21,"type":"Line","content":"97 21 97 21"},{"topY":0,"color":"0 0 0","topX":0,"rotation":0,"bottomX":97,"width":5,"bottomY":21,"type":"Line","content":"97 21 97 21"},{"topY":0,"color":"0 0 0","topX":0,"rotation":0,"bottomX":98,"width":5,"bottomY":21,"type":"Line","content":"98 21 98 21"},{"topY":0,"color":"0 0 0","topX":0,"rotation":0,"bottomX":99,"width":5,"bottomY":20,"type":"Line","content":"99 20 99 20"},{"topY":0,"color":"0 0 0","topX":0,"rotation":0,"bottomX":99,"width":5,"bottomY":19,"type":"Line","content":"99 19 99 19"},{"topY":0,"color":"0 0 0","topX":0,"rotation":0,"bottomX":100,"width":5,"bottomY":19,"type":"Line","content":"100 19 100 19"},{"topY":0,"color":"0 0 0","topX":0,"rotation":0,"bottomX":101,"width":5,"bottomY":17,"type":"Line","content":"101 17 101 17"},{"topY":0,"color":"0 0 0","topX":0,"rotation":0,"bottomX":102,"width":5,"bottomY":17,"type":"Line","content":"102 17 102 17"},{"topY":0,"color":"0 0 0","topX":0,"rotation":0,"bottomX":103,"width":5,"bottomY":16,"type":"Line","content":"103 16 103 16"},{"topY":0,"color":"0 0 0","topX":0,"rotation":0,"bottomX":104,"width":5,"bottomY":16,"type":"Line","content":"104 16 104 16"},{"topY":0,"color":"0 0 0","topX":0,"rotation":0,"bottomX":105,"width":5,"bottomY":15,"type":"Line","content":"105 15 105 15"},{"topY":0,"color":"0 0 0","topX":0,"rotation":0,"bottomX":105,"width":5,"bottomY":15,"type":"Line","content":"105 15 105 15"},{"topY":0,"color":"0 0 0","topX":0,"rotation":0,"bottomX":105,"width":5,"bottomY":14,"type":"Line","content":"105 14 105 14"},{"topY":0,"color":"0 0 0","topX":0,"rotation":0,"bottomX":106,"width":5,"bottomY":14,"type":"Line","content":"106 14 106 14"},{"topY":0,"color":"0 0 0","topX":0,"rotation":0,"bottomX":107,"width":5,"bottomY":14,"type":"Line","content":"107 14 107 14"},{"topY":0,"color":"0 0 0","topX":0,"rotation":0,"bottomX":107,"width":5,"bottomY":13,"type":"Line","content":"107 13 107 13"},{"topY":0,"color":"0 0 0","topX":0,"rotation":0,"bottomX":108,"width":5,"bottomY":12,"type":"Line","content":"108 12 108 12"},{"topY":0,"color":"0 0 0","topX":0,"rotation":0,"bottomX":109,"width":5,"bottomY":11,"type":"Line","content":"109 11 109 11"},{"topY":0,"color":"0 0 0","topX":0,"rotation":0,"bottomX":111,"width":5,"bottomY":9,"type":"Line","content":"111 9 111 9"},{"topY":0,"color":"0 0 0","topX":0,"rotation":0,"bottomX":111,"width":5,"bottomY":9,"type":"Line","content":"111 9 111 9"},{"topY":0,"color":"0 0 0","topX":0,"rotation":0,"bottomX":113,"width":5,"bottomY":7,"type":"Line","content":"113 7 113 7"},{"topY":0,"color":"0 0 0","topX":0,"rotation":0,"bottomX":113,"width":5,"bottomY":7,"type":"Line","content":"113 7 113 7"},{"topY":0,"color":"0 0 0","topX":0,"rotation":0,"bottomX":114,"width":5,"bottomY":6,"type":"Line","content":"114 6 114 6"},{"topY":0,"color":"0 0 0","topX":0,"rotation":0,"bottomX":114,"width":5,"bottomY":5,"type":"Line","content":"114 5 114 5"},{"topY":0,"color":"0 0 0","topX":0,"rotation":0,"bottomX":115,"width":5,"bottomY":5,"type":"Line","content":"115 5 115 5"},{"topY":0,"color":"0 0 0","topX":0,"rotation":0,"bottomX":115,"width":5,"bottomY":5,"type":"Line","content":"115 5 115 5"},{"topY":0,"color":"0 0 0","topX":0,"rotation":0,"bottomX":116,"width":5,"bottomY":5,"type":"Line","content":"116 5 116 5"},{"topY":0,"color":"0 0 0","topX":0,"rotation":0,"bottomX":117,"width":5,"bottomY":4,"type":"Line","content":"117 4 117 4"},{"topY":0,"color":"0 0 0","topX":0,"rotation":0,"bottomX":117,"width":5,"bottomY":3,"type":"Line","content":"117 3 117 3"},{"topY":0,"color":"0 0 0","topX":0,"rotation":0,"bottomX":119,"width":5,"bottomY":2,"type":"Line","content":"119 2 119 2"},{"topY":0,"color":"0 0 0","topX":0,"rotation":0,"bottomX":119,"width":5,"bottomY":1,"type":"Line","content":"119 1 119 1"},{"topY":0,"color":"0 0 0","topX":0,"rotation":0,"bottomX":119,"width":5,"bottomY":1,"type":"Line","content":"119 1 119 1"},{"topY":0,"color":"0 0 0","topX":0,"rotation":0,"bottomX":119,"width":5,"bottomY":1,"type":"Line","content":"119 1 119 1"},{"topY":0,"color":"0 0 0","topX":0,"rotation":0,"bottomX":120,"width":5,"bottomY":1,"type":"Line","content":"120 1 120 1"},{"topY":0,"color":"0 0 0","topX":0,"rotation":0,"bottomX":121,"width":5,"bottomY":1,"type":"Line","content":"121 1 121 1"},{"topY":0,"color":"0 0 0","topX":0,"rotation":0,"bottomX":121,"width":5,"bottomY":1,"type":"Line","content":"121 1 121 1"},{"topY":0,"color":"0 0 0","topX":0,"rotation":0,"bottomX":122,"width":5,"bottomY":0,"type":"Line","content":"122 0 122 0"},{"topY":-1,"color":"0 0 0","topX":0,"rotation":0,"bottomX":123,"width":5,"bottomY":0,"type":"Line","content":"123 -1 123 -1"},{"topY":-1,"color":"0 0 0","topX":0,"rotation":0,"bottomX":123,"width":5,"bottomY":0,"type":"Line","content":"123 -1 123 -1"},{"topY":-1,"color":"0 0 0","topX":0,"rotation":0,"bottomX":123,"width":5,"bottomY":0,"type":"Line","content":"123 -1 123 -1"},{"topY":-2,"color":"0 0 0","topX":0,"rotation":0,"bottomX":123,"width":5,"bottomY":0,"type":"Line","content":"123 -2 123 -2"},{"topY":-3,"color":"0 0 0","topX":0,"rotation":0,"bottomX":124,"width":5,"bottomY":0,"type":"Line","content":"124 -3 124 -3"},{"topY":-3,"color":"0 0 0","topX":0,"rotation":0,"bottomX":124,"width":5,"bottomY":0,"type":"Line","content":"124 -3 124 -3"},{"topY":-3,"color":"0 0 0","topX":0,"rotation":0,"bottomX":125,"width":5,"bottomY":0,"type":"Line","content":"125 -3 125 -3"},{"topY":-4,"color":"0 0 0","topX":0,"rotation":0,"bottomX":125,"width":5,"bottomY":0,"type":"Line","content":"125 -4 125 -4"},{"topY":-4,"color":"0 0 0","topX":0,"rotation":0,"bottomX":126,"width":5,"bottomY":0,"type":"Line","content":"126 -4 126 -4"},{"topY":-4,"color":"0 0 0","topX":0,"rotation":0,"bottomX":127,"width":5,"bottomY":0,"type":"Line","content":"127 -4 127 -4"},{"topY":-5,"color":"0 0 0","topX":0,"rotation":0,"bottomX":127,"width":5,"bottomY":0,"type":"Line","content":"127 -5 127 -5"},{"topY":-5,"color":"0 0 0","topX":0,"rotation":0,"bottomX":126,"width":5,"bottomY":0,"type":"Line","content":"126 -5 126 -5"},{"topY":-5,"color":"0 0 0","topX":0,"rotation":0,"bottomX":126,"width":5,"bottomY":0,"type":"Line","content":"126 -5 126 -5"},{"topY":-5,"color":"0 0 0","topX":0,"rotation":0,"bottomX":125,"width":5,"bottomY":0,"type":"Line","content":"125 -5 125 -5"},{"topY":-6,"color":"0 0 0","topX":0,"rotation":0,"bottomX":125,"width":5,"bottomY":0,"type":"Line","content":"125 -6 125 -6"},{"topY":0,"color":"0 0 0","topX":0,"rotation":0,"bottomX":1012,"width":5,"bottomY":166,"type":"Line","content":"1012 166 1012 166"},{"topY":0,"color":"0 0 0","topX":0,"rotation":0,"bottomX":1011,"width":5,"bottomY":166,"type":"Line","content":"1011 166 1011 166"},{"topY":0,"color":"0 0 0","topX":0,"rotation":0,"bottomX":1011,"width":5,"bottomY":167,"type":"Line","content":"1011 167 1011 167"},{"topY":0,"color":"0 0 0","topX":0,"rotation":0,"bottomX":1010,"width":5,"bottomY":168,"type":"Line","content":"1010 168 1010 168"},{"topY":0,"color":"0 0 0","topX":0,"rotation":0,"bottomX":1010,"width":5,"bottomY":169,"type":"Line","content":"1010 169 1010 169"},{"topY":0,"color":"0 0 0","topX":0,"rotation":0,"bottomX":1009,"width":5,"bottomY":170,"type":"Line","content":"1009 170 1009 170"},{"topY":0,"color":"0 0 0","topX":0,"rotation":0,"bottomX":1009,"width":5,"bottomY":171,"type":"Line","content":"1009 171 1009 171"},{"topY":0,"color":"0 0 0","topX":0,"rotation":0,"bottomX":1009,"width":5,"bottomY":171,"type":"Line","content":"1009 171 1009 171"},{"topY":0,"color":"0 0 0","topX":0,"rotation":0,"bottomX":1009,"width":5,"bottomY":171,"type":"Line","content":"1009 171 1009 171"},{"topY":0,"color":"0 0 0","topX":0,"rotation":0,"bottomX":1008,"width":5,"bottomY":172,"type":"Line","content":"1008 172 1008 172"},{"topY":0,"color":"0 0 0","topX":0,"rotation":0,"bottomX":1007,"width":5,"bottomY":173,"type":"Line","content":"1007 173 1007 173"},{"topY":0,"color":"0 0 0","topX":0,"rotation":0,"bottomX":1007,"width":5,"bottomY":173,"type":"Line","content":"1007 173 1007 173"},{"topY":0,"color":"0 0 0","topX":0,"rotation":0,"bottomX":1006,"width":5,"bottomY":174,"type":"Line","content":"1006 174 1006 174"},{"topY":0,"color":"0 0 0","topX":0,"rotation":0,"bottomX":1005,"width":5,"bottomY":175,"type":"Line","content":"1005 175 1005 175"},{"topY":0,"color":"0 0 0","topX":0,"rotation":0,"bottomX":1005,"width":5,"bottomY":175,"type":"Line","content":"1005 175 1005 175"},{"topY":0,"color":"0 0 0","topX":0,"rotation":0,"bottomX":1004,"width":5,"bottomY":176,"type":"Line","content":"1004 176 1004 176"},{"topY":0,"color":"0 0 0","topX":0,"rotation":0,"bottomX":1003,"width":5,"bottomY":177,"type":"Line","content":"1003 177 1003 177"},{"topY":0,"color":"0 0 0","topX":0,"rotation":0,"bottomX":1003,"width":5,"bottomY":177,"type":"Line","content":"1003 177 1003 177"},{"topY":0,"color":"0 0 0","topX":0,"rotation":0,"bottomX":1003,"width":5,"bottomY":178,"type":"Line","content":"1003 178 1003 178"},{"topY":0,"color":"0 0 0","topX":0,"rotation":0,"bottomX":1002,"width":5,"bottomY":179,"type":"Line","content":"1002 179 1002 179"},{"topY":0,"color":"0 0 0","topX":0,"rotation":0,"bottomX":1001,"width":5,"bottomY":179,"type":"Line","content":"1001 179 1001 179"},{"topY":0,"color":"0 0 0","topX":0,"rotation":0,"bottomX":1001,"width":5,"bottomY":179,"type":"Line","content":"1001 179 1001 179"},{"topY":0,"color":"0 0 0","topX":0,"rotation":0,"bottomX":1001,"width":5,"bottomY":180,"type":"Line","content":"1001 180 1001 180"},{"topY":0,"color":"0 0 0","topX":0,"rotation":0,"bottomX":1000,"width":5,"bottomY":181,"type":"Line","content":"1000 181 1000 181"},{"topY":0,"color":"0 0 0","topX":0,"rotation":0,"bottomX":999,"width":5,"bottomY":181,"type":"Line","content":"999 181 999 181"},{"topY":0,"color":"0 0 0","topX":0,"rotation":0,"bottomX":999,"width":5,"bottomY":182,"type":"Line","content":"999 182 999 182"},{"topY":0,"color":"0 0 0","topX":0,"rotation":0,"bottomX":998,"width":5,"bottomY":183,"type":"Line","content":"998 183 998 183"},{"topY":0,"color":"0 0 0","topX":0,"rotation":0,"bottomX":997,"width":5,"bottomY":183,"type":"Line","content":"997 183 997 183"},{"topY":0,"color":"0 0 0","topX":0,"rotation":0,"bottomX":997,"width":5,"bottomY":183,"type":"Line","content":"997 183 997 183"},{"topY":0,"color":"0 0 0","topX":0,"rotation":0,"bottomX":997,"width":5,"bottomY":184,"type":"Line","content":"997 184 997 184"},{"topY":0,"color":"0 0 0","topX":0,"rotation":0,"bottomX":996,"width":5,"bottomY":185,"type":"Line","content":"996 185 996 185"},{"topY":0,"color":"0 0 0","topX":0,"rotation":0,"bottomX":995,"width":5,"bottomY":185,"type":"Line","content":"995 185 995 185"},{"topY":0,"color":"0 0 0","topX":0,"rotation":0,"bottomX":995,"width":5,"bottomY":185,"type":"Line","content":"995 185 995 185"},{"topY":0,"color":"0 0 0","topX":0,"rotation":0,"bottomX":994,"width":5,"bottomY":185,"type":"Line","content":"994 185 994 185"},{"topY":0,"color":"0 0 0","topX":0,"rotation":0,"bottomX":993,"width":5,"bottomY":185,"type":"Line","content":"993 185 993 185"},{"topY":0,"color":"0 0 0","topX":0,"rotation":0,"bottomX":993,"width":5,"bottomY":186,"type":"Line","content":"993 186 993 186"},{"topY":0,"color":"0 0 0","topX":0,"rotation":0,"bottomX":993,"width":5,"bottomY":187,"type":"Line","content":"993 187 993 187"},{"topY":0,"color":"0 0 0","topX":0,"rotation":0,"bottomX":992,"width":5,"bottomY":187,"type":"Line","content":"992 187 992 187"},{"topY":0,"color":"0 0 0","topX":0,"rotation":0,"bottomX":991,"width":5,"bottomY":187,"type":"Line","content":"991 187 991 187"},{"topY":0,"color":"0 0 0","topX":0,"rotation":0,"bottomX":991,"width":5,"bottomY":188,"type":"Line","content":"991 188 991 188"},{"topY":0,"color":"0 0 0","topX":0,"rotation":0,"bottomX":991,"width":5,"bottomY":189,"type":"Line","content":"991 189 991 189"},{"topY":0,"color":"0 0 0","topX":0,"rotation":0,"bottomX":990,"width":5,"bottomY":189,"type":"Line","content":"990 189 990 189"},{"topY":0,"color":"0 0 0","topX":0,"rotation":0,"bottomX":989,"width":5,"bottomY":189,"type":"Line","content":"989 189 989 189"},{"topY":0,"color":"0 0 0","topX":0,"rotation":0,"bottomX":989,"width":5,"bottomY":189,"type":"Line","content":"989 189 989 189"},{"topY":0,"color":"0 0 0","topX":0,"rotation":0,"bottomX":989,"width":5,"bottomY":189,"type":"Line","content":"989 189 989 189"},{"topY":0,"color":"0 0 0","topX":0,"rotation":0,"bottomX":988,"width":5,"bottomY":189,"type":"Line","content":"988 189 988 189"},{"topY":0,"color":"0 0 0","topX":0,"rotation":0,"bottomX":987,"width":5,"bottomY":189,"type":"Line","content":"987 189 987 189"},{"topY":0,"color":"0 0 0","topX":0,"rotation":0,"bottomX":987,"width":5,"bottomY":190,"type":"Line","content":"987 190 987 190"},{"topY":0,"color":"0 0 0","topX":0,"rotation":0,"bottomX":987,"width":5,"bottomY":190,"type":"Line","content":"987 190 987 190"},{"topY":0,"color":"0 0 0","topX":0,"rotation":0,"bottomX":986,"width":5,"bottomY":190,"type":"Line","content":"986 190 986 190"},{"topY":0,"color":"0 0 0","topX":0,"rotation":0,"bottomX":986,"width":5,"bottomY":191,"type":"Line","content":"986 191 986 191"},{"topY":0,"color":"0 0 0","topX":0,"rotation":0,"bottomX":985,"width":5,"bottomY":191,"type":"Line","content":"985 191 985 191"},{"topY":0,"color":"0 0 0","topX":0,"rotation":0,"bottomX":985,"width":5,"bottomY":191,"type":"Line","content":"985 191 985 191"},{"topY":0,"color":"0 0 0","topX":0,"rotation":0,"bottomX":984,"width":5,"bottomY":192,"type":"Line","content":"984 192 984 192"},{"topY":0,"color":"0 0 0","topX":0,"rotation":0,"bottomX":983,"width":5,"bottomY":193,"type":"Line","content":"983 193 983 193"},{"topY":0,"color":"0 0 0","topX":0,"rotation":0,"bottomX":983,"width":5,"bottomY":193,"type":"Line","content":"983 193 983 193"},{"topY":0,"color":"0 0 0","topX":0,"rotation":0,"bottomX":982,"width":5,"bottomY":193,"type":"Line","content":"982 193 982 193"},{"topY":0,"color":"0 0 0","topX":0,"rotation":0,"bottomX":981,"width":5,"bottomY":194,"type":"Line","content":"981 194 981 194"},{"topY":0,"color":"0 0 0","topX":0,"rotation":0,"bottomX":981,"width":5,"bottomY":195,"type":"Line","content":"981 195 981 195"},{"topY":0,"color":"0 0 0","topX":0,"rotation":0,"bottomX":981,"width":5,"bottomY":195,"type":"Line","content":"981 195 981 195"},{"topY":0,"color":"0 0 0","topX":0,"rotation":0,"bottomX":980,"width":5,"bottomY":195,"type":"Line","content":"980 195 980 195"},{"topY":0,"color":"0 0 0","topX":0,"rotation":0,"bottomX":979,"width":5,"bottomY":195,"type":"Line","content":"979 195 979 195"},{"topY":0,"color":"0 0 0","topX":0,"rotation":0,"bottomX":978,"width":5,"bottomY":195,"type":"Line","content":"978 195 978 195"},{"topY":0,"color":"0 0 0","topX":0,"rotation":0,"bottomX":978,"width":5,"bottomY":196,"type":"Line","content":"978 196 978 196"},{"topY":0,"color":"0 0 0","topX":0,"rotation":0,"bottomX":977,"width":5,"bottomY":197,"type":"Line","content":"977 197 977 197"},{"topY":0,"color":"0 0 0","topX":0,"rotation":0,"bottomX":976,"width":5,"bottomY":197,"type":"Line","content":"976 197 976 197"},{"topY":0,"color":"0 0 0","topX":0,"rotation":0,"bottomX":976,"width":5,"bottomY":197,"type":"Line","content":"976 197 976 197"},{"topY":0,"color":"0 0 0","topX":0,"rotation":0,"bottomX":975,"width":5,"bottomY":198,"type":"Line","content":"975 198 975 198"},{"topY":0,"color":"0 0 0","topX":0,"rotation":0,"bottomX":974,"width":5,"bottomY":198,"type":"Line","content":"974 198 974 198"},{"topY":0,"color":"0 0 0","topX":0,"rotation":0,"bottomX":973,"width":5,"bottomY":199,"type":"Line","content":"973 199 973 199"},{"topY":0,"color":"0 0 0","topX":0,"rotation":0,"bottomX":973,"width":5,"bottomY":199,"type":"Line","content":"973 199 973 199"},{"topY":0,"color":"0 0 0","topX":0,"rotation":0,"bottomX":973,"width":5,"bottomY":199,"type":"Line","content":"973 199 973 199"},{"topY":0,"color":"0 0 0","topX":0,"rotation":0,"bottomX":972,"width":5,"bottomY":199,"type":"Line","content":"972 199 972 199"},{"topY":0,"color":"0 0 0","topX":0,"rotation":0,"bottomX":972,"width":5,"bottomY":200,"type":"Line","content":"972 200 972 200"},{"topY":0,"color":"0 0 0","topX":0,"rotation":0,"bottomX":971,"width":5,"bottomY":200,"type":"Line","content":"971 200 971 200"},{"topY":0,"color":"0 0 0","topX":0,"rotation":0,"bottomX":971,"width":5,"bottomY":201,"type":"Line","content":"971 201 971 201"},{"topY":0,"color":"0 0 0","topX":0,"rotation":0,"bottomX":971,"width":5,"bottomY":201,"type":"Line","content":"971 201 971 201"},{"topY":0,"color":"0 0 0","topX":0,"rotation":0,"bottomX":970,"width":5,"bottomY":202,"type":"Line","content":"970 202 970 202"},{"topY":0,"color":"0 0 0","topX":0,"rotation":0,"bottomX":969,"width":5,"bottomY":203,"type":"Line","content":"969 203 969 203"},{"topY":0,"color":"0 0 0","topX":0,"rotation":0,"bottomX":967,"width":5,"bottomY":205,"type":"Line","content":"967 205 967 205"},{"topY":0,"color":"0 0 0","topX":0,"rotation":0,"bottomX":966,"width":5,"bottomY":206,"type":"Line","content":"966 206 966 206"},{"topY":0,"color":"0 0 0","topX":0,"rotation":0,"bottomX":965,"width":5,"bottomY":207,"type":"Line","content":"965 207 965 207"},{"topY":0,"color":"0 0 0","topX":0,"rotation":0,"bottomX":963,"width":5,"bottomY":208,"type":"Line","content":"963 208 963 208"},{"topY":0,"color":"0 0 0","topX":0,"rotation":0,"bottomX":962,"width":5,"bottomY":209,"type":"Line","content":"962 209 962 209"},{"topY":0,"color":"0 0 0","topX":0,"rotation":0,"bottomX":961,"width":5,"bottomY":210,"type":"Line","content":"961 210 961 210"},{"topY":0,"color":"0 0 0","topX":0,"rotation":0,"bottomX":961,"width":5,"bottomY":211,"type":"Line","content":"961 211 961 211"},{"topY":0,"color":"0 0 0","topX":0,"rotation":0,"bottomX":959,"width":5,"bottomY":211,"type":"Line","content":"959 211 959 211"},{"topY":0,"color":"0 0 0","topX":0,"rotation":0,"bottomX":959,"width":5,"bottomY":212,"type":"Line","content":"959 212 959 212"},{"topY":0,"color":"0 0 0","topX":0,"rotation":0,"bottomX":958,"width":5,"bottomY":212,"type":"Line","content":"958 212 958 212"},{"topY":0,"color":"0 0 0","topX":0,"rotation":0,"bottomX":958,"width":5,"bottomY":213,"type":"Line","content":"958 213 958 213"},{"topY":0,"color":"0 0 0","topX":0,"rotation":0,"bottomX":957,"width":5,"bottomY":213,"type":"Line","content":"957 213 957 213"},{"topY":0,"color":"0 0 0","topX":0,"rotation":0,"bottomX":957,"width":5,"bottomY":214,"type":"Line","content":"957 214 957 214"},{"topY":0,"color":"0 0 0","topX":0,"rotation":0,"bottomX":955,"width":5,"bottomY":214,"type":"Line","content":"955 214 955 214"},{"topY":0,"color":"0 0 0","topX":0,"rotation":0,"bottomX":954,"width":5,"bottomY":216,"type":"Line","content":"954 216 954 216"},{"topY":0,"color":"0 0 0","topX":0,"rotation":0,"bottomX":953,"width":5,"bottomY":217,"type":"Line","content":"953 217 953 217"},{"topY":0,"color":"0 0 0","topX":0,"rotation":0,"bottomX":951,"width":5,"bottomY":219,"type":"Line","content":"951 219 951 219"},{"topY":0,"color":"0 0 0","topX":0,"rotation":0,"bottomX":948,"width":5,"bottomY":220,"type":"Line","content":"948 220 948 220"},{"topY":0,"color":"0 0 0","topX":0,"rotation":0,"bottomX":947,"width":5,"bottomY":221,"type":"Line","content":"947 221 947 221"},{"topY":0,"color":"0 0 0","topX":0,"rotation":0,"bottomX":945,"width":5,"bottomY":221,"type":"Line","content":"945 221 945 221"},{"topY":0,"color":"0 0 0","topX":0,"rotation":0,"bottomX":945,"width":5,"bottomY":223,"type":"Line","content":"945 223 945 223"},{"topY":0,"color":"0 0 0","topX":0,"rotation":0,"bottomX":944,"width":5,"bottomY":223,"type":"Line","content":"944 223 944 223"},{"topY":0,"color":"0 0 0","topX":0,"rotation":0,"bottomX":943,"width":5,"bottomY":224,"type":"Line","content":"943 224 943 224"},{"topY":0,"color":"0 0 0","topX":0,"rotation":0,"bottomX":943,"width":5,"bottomY":225,"type":"Line","content":"943 225 943 225"},{"topY":0,"color":"0 0 0","topX":0,"rotation":0,"bottomX":942,"width":5,"bottomY":225,"type":"Line","content":"942 225 942 225"},{"topY":0,"color":"0 0 0","topX":0,"rotation":0,"bottomX":941,"width":5,"bottomY":226,"type":"Line","content":"941 226 941 226"},{"topY":0,"color":"0 0 0","topX":0,"rotation":0,"bottomX":941,"width":5,"bottomY":227,"type":"Line","content":"941 227 941 227"},{"topY":0,"color":"0 0 0","topX":0,"rotation":0,"bottomX":939,"width":5,"bottomY":227,"type":"Line","content":"939 227 939 227"},{"topY":0,"color":"0 0 0","topX":0,"rotation":0,"bottomX":939,"width":5,"bottomY":228,"type":"Line","content":"939 228 939 228"},{"topY":0,"color":"0 0 0","topX":0,"rotation":0,"bottomX":938,"width":5,"bottomY":229,"type":"Line","content":"938 229 938 229"},{"topY":0,"color":"0 0 0","topX":0,"rotation":0,"bottomX":938,"width":5,"bottomY":229,"type":"Line","content":"938 229 938 229"},{"topY":0,"color":"0 0 0","topX":0,"rotation":0,"bottomX":937,"width":5,"bottomY":230,"type":"Line","content":"937 230 937 230"},{"topY":0,"color":"0 0 0","topX":0,"rotation":0,"bottomX":937,"width":5,"bottomY":231,"type":"Line","content":"937 231 937 231"},{"topY":0,"color":"0 0 0","topX":0,"rotation":0,"bottomX":936,"width":5,"bottomY":231,"type":"Line","content":"936 231 936 231"},{"topY":0,"color":"0 0 0","topX":0,"rotation":0,"bottomX":935,"width":5,"bottomY":231,"type":"Line","content":"935 231 935 231"},{"topY":0,"color":"0 0 0","topX":0,"rotation":0,"bottomX":935,"width":5,"bottomY":232,"type":"Line","content":"935 232 935 232"},{"topY":0,"color":"0 0 0","topX":0,"rotation":0,"bottomX":934,"width":5,"bottomY":233,"type":"Line","content":"934 233 934 233"},{"topY":0,"color":"0 0 0","topX":0,"rotation":0,"bottomX":934,"width":5,"bottomY":233,"type":"Line","content":"934 233 934 233"},{"topY":0,"color":"0 0 0","topX":0,"rotation":0,"bottomX":933,"width":5,"bottomY":235,"type":"Line","content":"933 235 933 235"},{"topY":0,"color":"0 0 0","topX":0,"rotation":0,"bottomX":931,"width":5,"bottomY":236,"type":"Line","content":"931 236 931 236"},{"topY":0,"color":"0 0 0","topX":0,"rotation":0,"bottomX":929,"width":5,"bottomY":237,"type":"Line","content":"929 237 929 237"},{"topY":0,"color":"0 0 0","topX":0,"rotation":0,"bottomX":928,"width":5,"bottomY":239,"type":"Line","content":"928 239 928 239"},{"topY":0,"color":"0 0 0","topX":0,"rotation":0,"bottomX":927,"width":5,"bottomY":240,"type":"Line","content":"927 240 927 240"},{"topY":0,"color":"0 0 0","topX":0,"rotation":0,"bottomX":926,"width":5,"bottomY":241,"type":"Line","content":"926 241 926 241"},{"topY":0,"color":"0 0 0","topX":0,"rotation":0,"bottomX":925,"width":5,"bottomY":241,"type":"Line","content":"925 241 925 241"},{"topY":0,"color":"0 0 0","topX":0,"rotation":0,"bottomX":925,"width":5,"bottomY":242,"type":"Line","content":"925 242 925 242"},{"topY":0,"color":"0 0 0","topX":0,"rotation":0,"bottomX":925,"width":5,"bottomY":243,"type":"Line","content":"925 243 925 243"},{"topY":0,"color":"0 0 0","topX":0,"rotation":0,"bottomX":924,"width":5,"bottomY":243,"type":"Line","content":"924 243 924 243"},{"topY":0,"color":"0 0 0","topX":0,"rotation":0,"bottomX":923,"width":5,"bottomY":243,"type":"Line","content":"923 243 923 243"},{"topY":0,"color":"0 0 0","topX":0,"rotation":0,"bottomX":923,"width":5,"bottomY":244,"type":"Line","content":"923 244 923 244"},{"topY":0,"color":"0 0 0","topX":0,"rotation":0,"bottomX":923,"width":5,"bottomY":244,"type":"Line","content":"923 244 923 244"},{"topY":0,"color":"0 0 0","topX":0,"rotation":0,"bottomX":922,"width":5,"bottomY":244,"type":"Line","content":"922 244 922 244"},{"topY":0,"color":"0 0 0","topX":0,"rotation":0,"bottomX":922,"width":5,"bottomY":245,"type":"Line","content":"922 245 922 245"},{"topY":0,"color":"0 0 0","topX":0,"rotation":0,"bottomX":921,"width":5,"bottomY":245,"type":"Line","content":"921 245 921 245"},{"topY":0,"color":"0 0 0","topX":0,"rotation":0,"bottomX":921,"width":5,"bottomY":246,"type":"Line","content":"921 246 921 246"},{"topY":0,"color":"0 0 0","topX":0,"rotation":0,"bottomX":920,"width":5,"bottomY":247,"type":"Line","content":"920 247 920 247"},{"topY":0,"color":"0 0 0","topX":0,"rotation":0,"bottomX":919,"width":5,"bottomY":248,"type":"Line","content":"919 248 919 248"},{"topY":0,"color":"0 0 0","topX":0,"rotation":0,"bottomX":918,"width":5,"bottomY":249,"type":"Line","content":"918 249 918 249"},{"topY":0,"color":"0 0 0","topX":0,"rotation":0,"bottomX":917,"width":5,"bottomY":250,"type":"Line","content":"917 250 917 250"},{"topY":0,"color":"0 0 0","topX":0,"rotation":0,"bottomX":917,"width":5,"bottomY":251,"type":"Line","content":"917 251 917 251"},{"topY":0,"color":"0 0 0","topX":0,"rotation":0,"bottomX":916,"width":5,"bottomY":251,"type":"Line","content":"916 251 916 251"},{"topY":0,"color":"0 0 0","topX":0,"rotation":0,"bottomX":915,"width":5,"bottomY":251,"type":"Line","content":"915 251 915 251"},{"topY":0,"color":"0 0 0","topX":0,"rotation":0,"bottomX":915,"width":5,"bottomY":251,"type":"Line","content":"915 251 915 251"},{"topY":0,"color":"0 0 0","topX":0,"rotation":0,"bottomX":915,"width":5,"bottomY":252,"type":"Line","content":"915 252 915 252"},{"topY":0,"color":"0 0 0","topX":0,"rotation":0,"bottomX":914,"width":5,"bottomY":252,"type":"Line","content":"914 252 914 252"},{"topY":0,"color":"0 0 0","topX":0,"rotation":0,"bottomX":914,"width":5,"bottomY":253,"type":"Line","content":"914 253 914 253"},{"topY":0,"color":"0 0 0","topX":0,"rotation":0,"bottomX":913,"width":5,"bottomY":253,"type":"Line","content":"913 253 913 253"},{"topY":0,"color":"0 0 0","topX":0,"rotation":0,"bottomX":912,"width":5,"bottomY":255,"type":"Line","content":"912 255 912 255"},{"topY":0,"color":"0 0 0","topX":0,"rotation":0,"bottomX":911,"width":5,"bottomY":255,"type":"Line","content":"911 255 911 255"},{"topY":0,"color":"0 0 0","topX":0,"rotation":0,"bottomX":909,"width":5,"bottomY":257,"type":"Line","content":"909 257 909 257"},{"topY":0,"color":"0 0 0","topX":0,"rotation":0,"bottomX":909,"width":5,"bottomY":257,"type":"Line","content":"909 257 909 257"},{"topY":0,"color":"0 0 0","topX":0,"rotation":0,"bottomX":908,"width":5,"bottomY":259,"type":"Line","content":"908 259 908 259"},{"topY":0,"color":"0 0 0","topX":0,"rotation":0,"bottomX":907,"width":5,"bottomY":259,"type":"Line","content":"907 259 907 259"},{"topY":0,"color":"0 0 0","topX":0,"rotation":0,"bottomX":907,"width":5,"bottomY":260,"type":"Line","content":"907 260 907 260"},{"topY":0,"color":"0 0 0","topX":0,"rotation":0,"bottomX":906,"width":5,"bottomY":260,"type":"Line","content":"906 260 906 260"},{"topY":0,"color":"0 0 0","topX":0,"rotation":0,"bottomX":905,"width":5,"bottomY":260,"type":"Line","content":"905 260 905 260"},{"topY":0,"color":"0 0 0","topX":0,"rotation":0,"bottomX":905,"width":5,"bottomY":261,"type":"Line","content":"905 261 905 261"},{"topY":0,"color":"0 0 0","topX":0,"rotation":0,"bottomX":905,"width":5,"bottomY":261,"type":"Line","content":"905 261 905 261"},{"topY":0,"color":"0 0 0","topX":0,"rotation":0,"bottomX":904,"width":5,"bottomY":261,"type":"Line","content":"904 261 904 261"},{"topY":0,"color":"0 0 0","topX":0,"rotation":0,"bottomX":904,"width":5,"bottomY":262,"type":"Line","content":"904 262 904 262"},{"topY":0,"color":"0 0 0","topX":0,"rotation":0,"bottomX":903,"width":5,"bottomY":263,"type":"Line","content":"903 263 903 263"},{"topY":0,"color":"0 0 0","topX":0,"rotation":0,"bottomX":903,"width":5,"bottomY":263,"type":"Line","content":"903 263 903 263"},{"topY":0,"color":"0 0 0","topX":0,"rotation":0,"bottomX":902,"width":5,"bottomY":263,"type":"Line","content":"902 263 902 263"},{"topY":0,"color":"0 0 0","topX":0,"rotation":0,"bottomX":901,"width":5,"bottomY":264,"type":"Line","content":"901 264 901 264"},{"topY":0,"color":"0 0 0","topX":0,"rotation":0,"bottomX":901,"width":5,"bottomY":264,"type":"Line","content":"901 264 901 264"},{"topY":0,"color":"0 0 0","topX":0,"rotation":0,"bottomX":901,"width":5,"bottomY":265,"type":"Line","content":"901 265 901 265"},{"topY":0,"color":"0 0 0","topX":0,"rotation":0,"bottomX":900,"width":5,"bottomY":265,"type":"Line","content":"900 265 900 265"},{"topY":0,"color":"0 0 0","topX":0,"rotation":0,"bottomX":899,"width":5,"bottomY":265,"type":"Line","content":"899 265 899 265"},{"topY":0,"color":"0 0 0","topX":0,"rotation":0,"bottomX":899,"width":5,"bottomY":266,"type":"Line","content":"899 266 899 266"},{"topY":0,"color":"0 0 0","topX":0,"rotation":0,"bottomX":899,"width":5,"bottomY":267,"type":"Line","content":"899 267 899 267"},{"topY":0,"color":"0 0 0","topX":0,"rotation":0,"bottomX":898,"width":5,"bottomY":267,"type":"Line","content":"898 267 898 267"},{"topY":0,"color":"0 0 0","topX":0,"rotation":0,"bottomX":897,"width":5,"bottomY":267,"type":"Line","content":"897 267 897 267"},{"topY":0,"color":"0 0 0","topX":0,"rotation":0,"bottomX":1013,"width":5,"bottomY":169,"type":"Line","content":"1013 169 1013 169"},{"topY":0,"color":"0 0 0","topX":0,"rotation":0,"bottomX":1014,"width":5,"bottomY":169,"type":"Line","content":"1014 169 1014 169"},{"topY":0,"color":"0 0 0","topX":0,"rotation":0,"bottomX":1015,"width":5,"bottomY":168,"type":"Line","content":"1015 168 1015 168"},{"topY":0,"color":"0 0 0","topX":0,"rotation":0,"bottomX":1015,"width":5,"bottomY":167,"type":"Line","content":"1015 167 1015 167"},{"topY":0,"color":"0 0 0","topX":0,"rotation":0,"bottomX":1016,"width":5,"bottomY":167,"type":"Line","content":"1016 167 1016 167"},{"topY":0,"color":"0 0 0","topX":0,"rotation":0,"bottomX":1017,"width":5,"bottomY":166,"type":"Line","content":"1017 166 1017 166"},{"topY":0,"color":"0 0 0","topX":0,"rotation":0,"bottomX":1017,"width":5,"bottomY":166,"type":"Line","content":"1017 166 1017 166"},{"topY":0,"color":"0 0 0","topX":0,"rotation":0,"bottomX":1017,"width":5,"bottomY":165,"type":"Line","content":"1017 165 1017 165"},{"topY":0,"color":"0 0 0","topX":0,"rotation":0,"bottomX":1018,"width":5,"bottomY":165,"type":"Line","content":"1018 165 1018 165"},{"topY":0,"color":"0 0 0","topX":0,"rotation":0,"bottomX":1019,"width":5,"bottomY":165,"type":"Line","content":"1019 165 1019 165"},{"topY":0,"color":"0 0 0","topX":0,"rotation":0,"bottomX":1019,"width":5,"bottomY":165,"type":"Line","content":"1019 165 1019 165"},{"topY":0,"color":"0 0 0","topX":0,"rotation":0,"bottomX":1020,"width":5,"bottomY":165,"type":"Line","content":"1020 165 1020 165"},{"topY":0,"color":"0 0 0","topX":0,"rotation":0,"bottomX":1020,"width":5,"bottomY":165,"type":"Line","content":"1020 165 1020 165"},{"topY":0,"color":"0 0 0","topX":0,"rotation":0,"bottomX":1020,"width":5,"bottomY":164,"type":"Line","content":"1020 164 1020 164"},{"topY":0,"color":"0 0 0","topX":0,"rotation":0,"bottomX":1021,"width":5,"bottomY":164,"type":"Line","content":"1021 164 1021 164"},{"topY":0,"color":"0 0 0","topX":0,"rotation":0,"bottomX":1021,"width":5,"bottomY":163,"type":"Line","content":"1021 163 1021 163"},{"topY":0,"color":"0 0 0","topX":0,"rotation":0,"bottomX":1021,"width":5,"bottomY":163,"type":"Line","content":"1021 163 1021 163"}],"background":{"topY":0,"topX":0,"rotation":0,"bottomX":1000,"bottomY":1000,"type":"Color","content":"255 255 255"}},"slides":[],"selectedSlide":0}